LICENSE.txt
README.md
setup.cfg
setup.py
KaggleToDatabricks/Authenticate.py
KaggleToDatabricks/TranfsformDataset.py
KaggleToDatabricks/__innit__.py
KaggleToDatabricks/test_Authenticate.py
KaggleToDatabricks/test_TransformDataset.py
KaggleToDatabricks.egg-info/PKG-INFO
KaggleToDatabricks.egg-info/SOURCES.txt
KaggleToDatabricks.egg-info/dependency_links.txt
KaggleToDatabricks.egg-info/requires.txt
KaggleToDatabricks.egg-info/top_level.txt