Metadata-Version: 2.1
Name: KaggleToDatabricks
Version: 0.8
Summary: Package created for recruitment task
Home-page: https://github.com/Teneb/kaggle_to_databricks
Download-URL: https://github.com/Teneb/kaggle_to_databricks/archive/refs/tags/v0.1.tar.gz
Author: Artur Woźniak
Author-email: arturwn39@gmail.com
License: MIT
Keywords: pls,hire,me
Classifier: Development Status :: 5 - Production/Stable
Classifier: Intended Audience :: Developers
Classifier: Topic :: Software Development :: Build Tools
Classifier: License :: OSI Approved :: MIT License
Classifier: Programming Language :: Python :: 3
Classifier: Programming Language :: Python :: 3.4
Classifier: Programming Language :: Python :: 3.5
Classifier: Programming Language :: Python :: 3.6
Classifier: Programming Language :: Python :: 3.7
Classifier: Programming Language :: Python :: 3.8
License-File: LICENSE.txt
